LICENSE
MANIFEST.in
README.md
setup.py
src/wheezy/__init__.py
src/wheezy.captcha.egg-info/PKG-INFO
src/wheezy.captcha.egg-info/SOURCES.txt
src/wheezy.captcha.egg-info/dependency_links.txt
src/wheezy.captcha.egg-info/namespace_packages.txt
src/wheezy.captcha.egg-info/not-zip-safe
src/wheezy.captcha.egg-info/requires.txt
src/wheezy.captcha.egg-info/top_level.txt
src/wheezy/captcha/__init__.py
src/wheezy/captcha/bezier.py
src/wheezy/captcha/comp.py
src/wheezy/captcha/http.py
src/wheezy/captcha/image.py
src/wheezy/captcha/mixin.py